spectromap/__init__.py
spectromap/spectromap.py
SpectroMap-1.0.2.dist-info/LICENSE
SpectroMap-1.0.2.dist-info/METADATA
SpectroMap-1.0.2.dist-info/WHEEL
SpectroMap-1.0.2.dist-info/top_level.txt
SpectroMap-1.0.2.dist-info/RECORD
