Metadata-Version: 2.1
Name: SpectroMap
Version: 1.0.2
Summary: SpectroMap is a peak detection algorithm that computes the constellation map for a given signal
Home-page: https://github.com/Aaron-AALG/SpectroMap
Download-URL: https://github.com/Aaron-AALG/SpectroMap/releases/tag/spectromap_1.0.0
Author: Aaron Lopez-Garcia
Author-email: aaron.lopez@uv.es
License: GPL-3.0
Classifier: Programming Language :: Python :: 3.8
Classifier: License :: OSI Approved :: GNU General Public License v3 (GPLv3)
License-File: LICENSE
Requires-Dist: numpy (>=1.19)
Requires-Dist: scipy (>=1.6.3)
